<?xml version='1.0' encoding='UTF-8'?>
<om:Sitting xmlns:om="http://www.openmunicipio.it" xmlns:xsi="http://www.w3.org/2001/XMLSchema-instance" xmlns:xlink="http://www.w3.org/1999/xlink" xsi:schemaLocation="http://www.openmunicipio.it DataImport.xsd" num="7" date="2010-04-14 11:46:57" call="1" site="C04">
  <om:Votation seq_n="1" votation_type="Palese Nominale" presents="36" partecipants="36" outcome="Approvato" legal_number="21" date_time="2010-04-14T00:00:00" counter_yes="21" counter_no="15" counter_abs="0">
    <om:Subject sintetic="proposta di rinvio"><![CDATA[proposta di rinvio]]></om:Subject>
    <om:Votes>
      <om:ChargeVote cardID="4" componentId="4" vote="EAB">
        <om:ChargeXRef xlink:href="./people.xml#4" xlink:type="simple"/>
      </om:ChargeVote>
      <om:ChargeVote cardID="17" componentId="17" vote="FAV">
        <om:ChargeXRef xlink:href="./people.xml#17" xlink:type="simple"/>
      </om:ChargeVote>
      <om:ChargeVote cardID="20" componentId="20" vote="EAB">
        <om:ChargeXRef xlink:href="./people.xml#20" xlink:type="simple"/>
      </om:ChargeVote>
      <om:ChargeVote cardID="22" componentId="22" vote="FAV">
        <om:ChargeXRef xlink:href="./people.xml#22" xlink:type="simple"/>
      </om:ChargeVote>
      <om:ChargeVote cardID="25" componentId="25" vote="CON">
        <om:ChargeXRef xlink:href="./people.xml#25" xlink:type="simple"/>
      </om:ChargeVote>
      <om:ChargeVote cardID="26" componentId="26" vote="FAV">
        <om:ChargeXRef xlink:href="./people.xml#26" xlink:type="simple"/>
      </om:ChargeVote>
      <om:ChargeVote cardID="27" componentId="27" vote="EAB">
        <om:ChargeXRef xlink:href="./people.xml#27" xlink:type="simple"/>
      </om:ChargeVote>
      <om:ChargeVote cardID="28" componentId="28" vote="FAV">
        <om:ChargeXRef xlink:href="./people.xml#28" xlink:type="simple"/>
      </om:ChargeVote>
      <om:ChargeVote cardID="29" componentId="29" vote="CON">
        <om:ChargeXRef xlink:href="./people.xml#29" xlink:type="simple"/>
      </om:ChargeVote>
      <om:ChargeVote cardID="33" componentId="33" vote="EAB">
        <om:ChargeXRef xlink:href="./people.xml#33" xlink:type="simple"/>
      </om:ChargeVote>
      <om:ChargeVote cardID="36" componentId="36" vote="CON">
        <om:ChargeXRef xlink:href="./people.xml#36" xlink:type="simple"/>
      </om:ChargeVote>
      <om:ChargeVote cardID="41" componentId="41" vote="EAB">
        <om:ChargeXRef xlink:href="./people.xml#41" xlink:type="simple"/>
      </om:ChargeVote>
      <om:ChargeVote cardID="49" componentId="49" vote="EAB">
        <om:ChargeXRef xlink:href="./people.xml#49" xlink:type="simple"/>
      </om:ChargeVote>
      <om:ChargeVote cardID="53" componentId="53" vote="EAB">
        <om:ChargeXRef xlink:href="./people.xml#53" xlink:type="simple"/>
      </om:ChargeVote>
      <om:ChargeVote cardID="54" componentId="54" vote="EAB">
        <om:ChargeXRef xlink:href="./people.xml#54" xlink:type="simple"/>
      </om:ChargeVote>
      <om:ChargeVote cardID="59" componentId="59" vote="FAV">
        <om:ChargeXRef xlink:href="./people.xml#59" xlink:type="simple"/>
      </om:ChargeVote>
      <om:ChargeVote cardID="60" componentId="60" vote="CON">
        <om:ChargeXRef xlink:href="./people.xml#60" xlink:type="simple"/>
      </om:ChargeVote>
      <om:ChargeVote cardID="61" componentId="61" vote="FAV">
        <om:ChargeXRef xlink:href="./people.xml#61" xlink:type="simple"/>
      </om:ChargeVote>
      <om:ChargeVote cardID="63" componentId="63" vote="FAV">
        <om:ChargeXRef xlink:href="./people.xml#63" xlink:type="simple"/>
      </om:ChargeVote>
      <om:ChargeVote cardID="64" componentId="64" vote="FAV">
        <om:ChargeXRef xlink:href="./people.xml#64" xlink:type="simple"/>
      </om:ChargeVote>
      <om:ChargeVote cardID="69" componentId="69" vote="EAB">
        <om:ChargeXRef xlink:href="./people.xml#69" xlink:type="simple"/>
      </om:ChargeVote>
      <om:ChargeVote cardID="70" componentId="70" vote="CON">
        <om:ChargeXRef xlink:href="./people.xml#70" xlink:type="simple"/>
      </om:ChargeVote>
    </om:Votes>
  </om:Votation>
</om:Sitting>
